diffenator2/__init__.py
diffenator2/__main__.py
diffenator2/_diffbrowsers.py
diffenator2/_diffenator.py
diffenator2/data/test_strings.json
diffenator2/data/udhr_all.txt
diffenator2/data/wordlists/Adlam.txt
diffenator2/data/wordlists/Arabic.txt
diffenator2/data/wordlists/Armenian.txt
diffenator2/data/wordlists/Avestan.txt
diffenator2/data/wordlists/Bengali.txt
diffenator2/data/wordlists/Bopomofo.txt
diffenator2/data/wordlists/Canadian_Aboriginal.txt
diffenator2/data/wordlists/Chakma.txt
diffenator2/data/wordlists/Cherokee.txt
diffenator2/data/wordlists/Common.txt
diffenator2/data/wordlists/Cyrillic.txt
diffenator2/data/wordlists/Devanagari.txt
diffenator2/data/wordlists/Ethiopic.txt
diffenator2/data/wordlists/Georgian.txt
diffenator2/data/wordlists/Greek.txt
diffenator2/data/wordlists/Gujarati.txt
diffenator2/data/wordlists/Gurmukhi.txt
diffenator2/data/wordlists/Hebrew.txt
diffenator2/data/wordlists/Hiragana.txt
diffenator2/data/wordlists/Japanese.txt
diffenator2/data/wordlists/Katakana.txt
diffenator2/data/wordlists/Khmer.txt
diffenator2/data/wordlists/Lao.txt
diffenator2/data/wordlists/Latin.txt
diffenator2/data/wordlists/Lisu.txt
diffenator2/data/wordlists/Malayalam.txt
diffenator2/data/wordlists/Mongolian.txt
diffenator2/data/wordlists/Myanmar.txt
diffenator2/data/wordlists/Ol_Chiki.txt
diffenator2/data/wordlists/Oriya.txt
diffenator2/data/wordlists/Osage.txt
diffenator2/data/wordlists/Sinhala.txt
diffenator2/data/wordlists/Syriac.txt
diffenator2/data/wordlists/Tamil.txt
diffenator2/data/wordlists/Telugu.txt
diffenator2/data/wordlists/Thai.txt
diffenator2/data/wordlists/Thanaa.txt
diffenator2/data/wordlists/Tibetan.txt
diffenator2/data/wordlists/Tifinagh.txt
diffenator2/data/wordlists/Vai.txt
diffenator2/font.py
diffenator2/html.py
diffenator2/jfont.py
diffenator2/masters.py
diffenator2/matcher.py
diffenator2/renderer.py
diffenator2/screenshot.py
diffenator2/segmenting.py
diffenator2/shape.py
diffenator2/template_elements.py
diffenator2-0.4.2.dist-info/AUTHORS.txt
diffenator2-0.4.2.dist-info/LICENSE.txt
diffenator2-0.4.2.dist-info/METADATA
diffenator2-0.4.2.dist-info/WHEEL
diffenator2-0.4.2.dist-info/entry_points.txt
diffenator2-0.4.2.dist-info/RECORD
