Metadata-Version: 2.1
Name: diffenator2
Version: 0.4.2
Summary: Compare two fonts
Author: Marc Foley
Author-email: m.foley.88@gmail.com
Requires-Python: >=3.8,<4.0
Classifier: Programming Language :: Python :: 3
Classifier: Programming Language :: Python :: 3.8
Classifier: Programming Language :: Python :: 3.9
Classifier: Programming Language :: Python :: 3.10
Classifier: Programming Language :: Python :: 3.11
Classifier: Programming Language :: Python :: 3.12
Requires-Dist: Pillow
Requires-Dist: blackrenderer[skia] (>=0.6.0,<0.7.0)
Requires-Dist: fontTools[ufo] (>=4.37.3)
Requires-Dist: freetype-py
Requires-Dist: gflanguages
Requires-Dist: glyphsets (>=0.6.5)
Requires-Dist: jinja2
Requires-Dist: ninja
Requires-Dist: protobuf (>=3.19.2,<=3.20.3)
Requires-Dist: pyahocorasick
Requires-Dist: python-bidi
Requires-Dist: selenium (>=4.4.3)
Requires-Dist: tqdm (>=4.64.1,<5.0.0)
Requires-Dist: uharfbuzz
Requires-Dist: unicodedata2 (>=15.0.0,<16.0.0)
Requires-Dist: youseedee (>=0.5.0,<0.6.0)
